<?xml version="1.0" encoding="UTF-8"?><record_update>
    <sys_choice action="INSERT_OR_UPDATE" field="status" table="x_1233104_print_0_job_order" version="3">
        <sys_choice_set action="INSERT_OR_UPDATE">
            <element>status</element>
            <name>x_1233104_print_0_job_order</name>
            <sys_class_name>sys_choice_set</sys_class_name>
            <sys_created_by>admin</sys_created_by>
            <sys_created_on>2025-07-25 12:07:16</sys_created_on>
            <sys_mod_count>0</sys_mod_count>
            <sys_name>status</sys_name>
            <sys_package display_value="Print Production Management App" source="x_1233104_print_0">3fc4d204938722107f067baefaba10de</sys_package>
            <sys_policy/>
            <sys_scope display_value="Print Production Management App">3fc4d204938722107f067baefaba10de</sys_scope>
            <sys_update_name>sys_choice_x_1233104_print_0_job_order_status</sys_update_name>
            <sys_updated_by>admin</sys_updated_by>
            <sys_updated_on>2025-07-25 12:07:16</sys_updated_on>
        </sys_choice_set>
        <sys_choice action="INSERT_OR_UPDATE">
            <dependent_value/>
            <element>status</element>
            <hint/>
            <inactive>false</inactive>
            <label>Awaiting Design Approval</label>
            <language>en</language>
            <name>x_1233104_print_0_job_order</name>
            <sequence>0</sequence>
            <synonyms/>
            <sys_created_by>admin</sys_created_by>
            <sys_created_on>2025-07-25 12:07:16</sys_created_on>
            <sys_domain>global</sys_domain>
            <sys_domain_path>/</sys_domain_path>
            <sys_mod_count>1</sys_mod_count>
            <sys_updated_by>admin</sys_updated_by>
            <sys_updated_on>2025-07-26 10:53:09</sys_updated_on>
            <value>awaiting_design_approval</value>
        </sys_choice>
        <sys_choice action="INSERT_OR_UPDATE">
            <dependent_value/>
            <element>status</element>
            <hint/>
            <inactive>false</inactive>
            <label>Awaiting Payment</label>
            <language>en</language>
            <name>x_1233104_print_0_job_order</name>
            <sequence>1</sequence>
            <synonyms/>
            <sys_created_by>admin</sys_created_by>
            <sys_created_on>2025-07-25 12:07:16</sys_created_on>
            <sys_domain>global</sys_domain>
            <sys_domain_path>/</sys_domain_path>
            <sys_mod_count>1</sys_mod_count>
            <sys_updated_by>admin</sys_updated_by>
            <sys_updated_on>2025-07-26 10:53:09</sys_updated_on>
            <value>awaiting_payment</value>
        </sys_choice>
        <sys_choice action="INSERT_OR_UPDATE">
            <dependent_value/>
            <element>status</element>
            <hint/>
            <inactive>false</inactive>
            <label>Design appoved for printing</label>
            <language>en</language>
            <name>x_1233104_print_0_job_order</name>
            <sequence>2</sequence>
            <synonyms/>
            <sys_created_by>admin</sys_created_by>
            <sys_created_on>2025-07-25 12:07:16</sys_created_on>
            <sys_domain>global</sys_domain>
            <sys_domain_path>/</sys_domain_path>
            <sys_mod_count>2</sys_mod_count>
            <sys_updated_by>admin</sys_updated_by>
            <sys_updated_on>2025-08-13 10:49:31</sys_updated_on>
            <value>client_approval</value>
        </sys_choice>
        <sys_choice action="INSERT_OR_UPDATE">
            <dependent_value/>
            <element>status</element>
            <hint/>
            <inactive>false</inactive>
            <label>Completed</label>
            <language>en</language>
            <name>x_1233104_print_0_job_order</name>
            <sequence>3</sequence>
            <synonyms/>
            <sys_created_by>admin</sys_created_by>
            <sys_created_on>2025-07-25 12:07:16</sys_created_on>
            <sys_domain>global</sys_domain>
            <sys_domain_path>/</sys_domain_path>
            <sys_mod_count>1</sys_mod_count>
            <sys_updated_by>admin</sys_updated_by>
            <sys_updated_on>2025-07-26 10:53:09</sys_updated_on>
            <value>completed</value>
        </sys_choice>
        <sys_choice action="INSERT_OR_UPDATE">
            <dependent_value/>
            <element>status</element>
            <hint/>
            <inactive>false</inactive>
            <label>In Design</label>
            <language>en</language>
            <name>x_1233104_print_0_job_order</name>
            <sequence>4</sequence>
            <synonyms/>
            <sys_created_by>admin</sys_created_by>
            <sys_created_on>2025-07-25 12:07:16</sys_created_on>
            <sys_domain>global</sys_domain>
            <sys_domain_path>/</sys_domain_path>
            <sys_mod_count>1</sys_mod_count>
            <sys_updated_by>admin</sys_updated_by>
            <sys_updated_on>2025-07-26 10:53:09</sys_updated_on>
            <value>in_design</value>
        </sys_choice>
        <sys_choice action="INSERT_OR_UPDATE">
            <dependent_value/>
            <element>status</element>
            <hint/>
            <inactive>false</inactive>
            <label>New</label>
            <language>en</language>
            <name>x_1233104_print_0_job_order</name>
            <sequence>5</sequence>
            <synonyms/>
            <sys_created_by>admin</sys_created_by>
            <sys_created_on>2025-07-25 12:07:16</sys_created_on>
            <sys_domain>global</sys_domain>
            <sys_domain_path>/</sys_domain_path>
            <sys_mod_count>1</sys_mod_count>
            <sys_updated_by>admin</sys_updated_by>
            <sys_updated_on>2025-07-26 10:53:09</sys_updated_on>
            <value>new</value>
        </sys_choice>
        <sys_choice action="INSERT_OR_UPDATE">
            <dependent_value/>
            <element>status</element>
            <hint/>
            <inactive>false</inactive>
            <label>Printing</label>
            <language>en</language>
            <name>x_1233104_print_0_job_order</name>
            <sequence>6</sequence>
            <synonyms/>
            <sys_created_by>admin</sys_created_by>
            <sys_created_on>2025-07-25 12:07:16</sys_created_on>
            <sys_domain>global</sys_domain>
            <sys_domain_path>/</sys_domain_path>
            <sys_mod_count>1</sys_mod_count>
            <sys_updated_by>admin</sys_updated_by>
            <sys_updated_on>2025-07-26 10:53:09</sys_updated_on>
            <value>printing</value>
        </sys_choice>
    </sys_choice>
</record_update>
